btd/__init__.py
btd-3.0.dist-info/licenses/LICENSE
btd-3.0.dist-info/METADATA
btd-3.0.dist-info/WHEEL
btd-3.0.dist-info/top_level.txt
btd-3.0.dist-info/RECORD
