Metadata-Version: 2.4
Name: btd
Version: 3.0
Summary: BTD — Binary To Data: Ferramentas para salvar arquivos .btd
Home-page: 
Author: TheGhost
Author-email: gabriel.gamerx11g@gmail.com
Classifier: Programming Language :: Python :: 3
Classifier: License :: OSI Approved :: MIT License
Classifier: Operating System :: OS Independent
Requires-Python: >=3.7
License-File: LICENSE
Dynamic: author
Dynamic: author-email
Dynamic: classifier
Dynamic: description
Dynamic: description-content-type
Dynamic: license-file
Dynamic: requires-python
Dynamic: summary
